{
  "challenges": [
    {"id": "1", "type": "normal", "text_pt": "Se você já mentiu para um amigo, beba 2 goles", "text_en": "If you've ever lied to a friend, take 2 sips", "sips": 2},
    {"id": "2", "type": "normal", "text_pt": "Se você já chegou mais de 30 min atrasado, beba 3 goles", "text_en": "If you've been more than 30 min late, take 3 sips", "sips": 3},
    {"id": "3", "type": "normal", "text_pt": "Se você já esqueceu o nome de alguém, beba 1 gole", "text_en": "If you've forgotten someone's name, take 1 sip", "sips": 1},
    {"id": "4", "type": "normal", "text_pt": "Se você acredita em fantasmas, beba 2 goles", "text_en": "If you believe in ghosts, take 2 sips", "sips": 2},
    {"id": "5", "type": "normal", "text_pt": "Se você já fingiu estar doente para faltar, beba 3 goles", "text_en": "If you've ever called in sick when you weren't, take 3 sips", "sips": 3},
    {"id": "6", "type": "normal", "text_pt": "Se você consegue tocar o nariz com a língua, dê 4 goles para alguém", "text_en": "If you can touch your nose with your tongue, give 4 sips to someone", "sips": 0, "give_sips": true, "give_sips_amount": 4},
    {"id": "7", "type": "normal", "text_pt": "Se você já chorou assistindo filme, beba 2 goles", "text_en": "If you've cried watching a movie, take 2 sips", "sips": 2},
    {"id": "8", "type": "normal", "text_pt": "Se você dorme de barriga pra cima, beba 1 gole", "text_en": "If you sleep on your back, take 1 sip", "sips": 1},
    {"id": "9", "type": "normal", "text_pt": "Se você já enviou mensagem errada, dê 3 goles para quem quiser", "text_en": "If you've sent a text to the wrong person, give 3 sips to whoever you want", "sips": 0, "give_sips": true, "give_sips_amount": 3},
    {"id": "10", "type": "normal", "text_pt": "Se você já comeu algo do chão, beba 4 goles", "text_en": "If you've eaten something off the floor, take 4 sips", "sips": 4},
    {"id": "11", "type": "normal", "text_pt": "Se você já ficou preso em um elevador, beba 2 goles", "text_en": "If you've been stuck in an elevator, take 2 sips", "sips": 2},
    {"id": "12", "type": "normal", "text_pt": "Se você já ligou para a pessoa errada e deixou recado, beba 3 goles", "text_en": "If you've called the wrong number and left a voicemail, take 3 sips", "sips": 3},
    {"id": "13", "type": "normal", "text_pt": "Se você já foi reconhecido por alguém que você não lembra, beba 2 goles", "text_en": "If you've been recognized by someone you don't remember, take 2 sips", "sips": 2},
    {"id": "14", "type": "normal", "text_pt": "Se você já usou roupa do avesso o dia todo, beba 3 goles", "text_en": "If you've worn clothes inside out all day, take 3 sips", "sips": 3},
    {"id": "15", "type": "normal", "text_pt": "Se você já dormiu em público, beba 2 goles", "text_en": "If you've fallen asleep in public, take 2 sips", "sips": 2},
    {"id": "16", "type": "normal", "text_pt": "Se você já deu um abraço na pessoa errada, beba 1 gole", "text_en": "If you've hugged the wrong person, take 1 sip", "sips": 1},
    {"id": "17", "type": "normal", "text_pt": "Se você já tentou assobiar e não conseguiu, beba 2 goles", "text_en": "If you've tried to whistle and failed, take 2 sips", "sips": 2},
    {"id": "18", "type": "normal", "text_pt": "Se você já tropeçou em nada, beba 1 gole", "text_en": "If you've tripped over nothing, take 1 sip", "sips": 1},
    {"id": "19", "type": "normal", "text_pt": "Se você já respondeu uma pergunta errada em voz alta, beba 3 goles", "text_en": "If you've answered a question wrong out loud, take 3 sips", "sips": 3},
    {"id": "20", "type": "normal", "text_pt": "Se você já mandou 'eu te amo' para a pessoa errada, beba 4 goles", "text_en": "If you've sent 'I love you' to the wrong person, take 4 sips", "sips": 4},
    {"id": "21", "type": "normal", "text_pt": "Se você já fingiu que estava ao telefone para evitar conversa, beba 2 goles", "text_en": "If you've pretended to be on the phone to avoid conversation, take 2 sips", "sips": 2},
    {"id": "22", "type": "normal", "text_pt": "Se você já comeu a comida de outra pessoa sem pedir, beba 3 goles", "text_en": "If you've eaten someone else's food without asking, take 3 sips", "sips": 3},
    {"id": "23", "type": "normal", "text_pt": "Se você já levantou da cama e bateu o pé na quina, dê 5 goles para quem quiser", "text_en": "If you've stubbed your toe on a corner, give 5 sips to whoever you want", "sips": 0, "give_sips": true, "give_sips_amount": 5},
    {"id": "24", "type": "normal", "text_pt": "Se você já caiu da cadeira, beba 3 goles", "text_en": "If you've fallen off a chair, take 3 sips", "sips": 3},
    {"id": "25", "type": "normal", "text_pt": "Se você já fingiu que não viu a mensagem de alguém, beba 2 goles", "text_en": "If you've pretended you didn't see someone's message, take 2 sips", "sips": 2},

    {"id": "26", "type": "game", "text_pt": "Todos devem apontar para quem acham que é o pior mentiroso. Quem receber mais votos bebe 5 goles!", "text_en": "Everyone point at who you think is the biggest liar. Most votes drinks 5 sips!", "sips": 5},
    {"id": "27", "type": "game", "text_pt": "Todos devem dizer ao mesmo tempo um número de 1 a 10. Quem mais se aproximar do número secreto de {player} ganha e distribui 3 goles!", "text_en": "Everyone say a number from 1 to 10 at the same time. Closest to {player}'s secret number wins and distributes 3 sips!", "sips": 3},
    {"id": "28", "type": "game", "text_pt": "Todos devem fazer sua melhor imitação de um animal. {player} escolhe o pior e esse bebe 4 goles!", "text_en": "Everyone do your best animal impression. {player} picks the worst and that person drinks 4 sips!", "sips": 4},
    {"id": "29", "type": "game", "text_pt": "Vai passando uma moeda e cada um diz uma fruta. Quem repetir ou demorar mais de 3 segundos bebe 2 goles!", "text_en": "Pass a coin around and each person names a fruit. Anyone who repeats or takes more than 3 seconds drinks 2 sips!", "sips": 2},
    {"id": "30", "type": "game", "text_pt": "Todos devem dizer ao mesmo tempo um tipo de música. Quem mais combinar com {player} bebe 3 goles!", "text_en": "Everyone say a music genre at the same time. Most matching with {player} drinks 3 sips!", "sips": 3},
    {"id": "31", "type": "game", "text_pt": "Vai passando uma moeda e cada um diz um animal. Quem falar o mesmo que outro bebe 2 goles!", "text_en": "Pass a coin around and each person names an animal. Anyone who picks the same as someone else drinks 2 sips!", "sips": 2},
    {"id": "32", "type": "game", "text_pt": "Todos devem dizer ao mesmo tempo uma comida. Quem mais combinar com {player} ganha! O resto bebe 2 goles!", "text_en": "Everyone say a food at the same time. Most matching with {player} wins! The rest drink 2 sips!", "sips": 2},
    {"id": "33", "type": "game", "text_pt": "Vai passando uma moeda e cada um diz um país. Quem repetir ou não conseguir pensar bebe 3 goles!", "text_en": "Pass a coin around and each person names a country. Anyone who repeats or can't think of one drinks 3 sips!", "sips": 3},
    {"id": "34", "type": "game", "text_pt": "Todos devem dizer ao mesmo tempo um número de 1 a 5. Quem mais combinar bebe 2 goles!", "text_en": "Everyone say a number from 1 to 5 at the same time. Most matching drinks 2 sips!", "sips": 2},
    {"id": "35", "type": "game", "text_pt": "Vai passando uma moeda e cada um diz um nome de celebridade. Quem repetir bebe 2 goles!", "text_en": "Pass a coin around and each person names a celebrity. Anyone who repeats drinks 2 sips!", "sips": 2},
    {"id": "36", "type": "game", "text_pt": "Vai passando uma moeda e cada um diz um mês do ano. Quem repetir bebe 2 goles!", "text_en": "Pass a coin around and each person names a month. Anyone who repeats drinks 2 sips!", "sips": 2},
    {"id": "37", "type": "game", "text_pt": "Vai passando uma moeda e cada um diz um dos 5 sentidos. Quem repetir bebe 2 goles!", "text_en": "Pass a coin and each person names one of the 5 senses. Anyone who repeats drinks 2 sips!", "sips": 2},
    {"id": "38", "type": "game", "text_pt": "Vai passando uma moeda e cada um diz uma profissão. Quem repetir bebe 2 goles!", "text_en": "Pass a coin and each person names a profession. Anyone who repeats drinks 2 sips!", "sips": 2},
    {"id": "39", "type": "game", "text_pt": "Vai passando uma moeda e cada um diz um continente. Quem errar bebe 3 goles!", "text_en": "Pass a coin and each person names a continent. Anyone who gets it wrong drinks 3 sips!", "sips": 3},
    {"id": "40", "type": "game", "text_pt": "Todos devem dizer ao mesmo tempo uma bebida. Quem mais combinar com {player} bebe 4 goles!", "text_en": "Everyone say a drink at the same time. Most matching with {player} drinks 4 sips!", "sips": 4},

    {"id": "41", "type": "virus_start", "text_pt": "{player}, crie uma regra e escolha quem deve segui-la. O vírus começa agora!", "text_en": "{player}, make up a rule and choose who must follow it. The virus starts now!"},
    {"id": "42", "type": "virus_end", "text_pt": "Regra acabou! Todos podem voltar ao normal.", "text_en": "Rule over! Everyone can go back to normal."},
    {"id": "43", "type": "virus_start", "text_pt": "Agora você só pode falar em tom de voz baixo. Se gritar, bebe 2 goles!", "text_en": "You can only speak in a low voice now. If you raise your voice, drink 2 sips!", "sips": 2},
    {"id": "44", "type": "virus_end", "text_pt": "Pode falar normalmente agora! O vírus acabou.", "text_en": "You can speak normally now! The virus is over."},
    {"id": "45", "type": "virus_start", "text_pt": "Agora você só pode falar em perguntas. Se falar uma frase normal, bebe 3 goles!", "text_en": "You can only speak in questions now. If you make a normal statement, drink 3 sips!", "sips": 3},
    {"id": "46", "type": "virus_end", "text_pt": "Pode falar normalmente agora! O vírus acabou.", "text_en": "You can speak normally now! The virus is over."},
    {"id": "47", "type": "virus_start", "text_pt": "Agora você só pode responder com 'sim' ou 'não'. O vírus começa agora!", "text_en": "You can only answer 'yes' or 'no' now. The virus starts now!"},
    {"id": "48", "type": "virus_end", "text_pt": "Liberdade total! O vírus acabou.", "text_en": "Total freedom! The virus is over."},
    {"id": "49", "type": "virus_start", "text_pt": "Agora você deve chamar todo mundo pelo nome de alguma fruta. Se esquecer, bebe 2 goles!", "text_en": "You must now call everyone by a fruit name. If you forget, drink 2 sips!", "sips": 2},
    {"id": "50", "type": "virus_end", "text_pt": "Pode chamar pelo nome de agora! O vírus acabou.", "text_en": "You can use real names now! The virus is over."},
    {"id": "51", "type": "virus_start", "text_pt": "Agora você só pode andar de costas. Se virar, bebe 2 goles!", "text_en": "You can only walk backwards now. If you turn around, drink 2 sips!", "sips": 2},
    {"id": "52", "type": "virus_end", "text_pt": "Pode andar normalmente! O vírus acabou.", "text_en": "You can walk normally now! The virus is over."},
    {"id": "53", "type": "virus_start", "text_pt": "Agora você deve rir depois de cada fala. Se esquecer, bebe 2 goles!", "text_en": "You must now laugh after every sentence. If you forget, drink 2 sips!", "sips": 2},
    {"id": "54", "type": "virus_end", "text_pt": "Pode parar de rir agora! O vírus acabou.", "text_en": "You can stop laughing now! The virus is over."},
    {"id": "55", "type": "virus_start", "text_pt": "Agora você só pode falar com as mãos. Se falar com a voz, bebe 2 goles!", "text_en": "You can only speak with your hands now. If you use your voice, drink 2 sips!", "sips": 2},
    {"id": "56", "type": "virus_end", "text_pt": "Pode falar com a voz agora! O vírus acabou.", "text_en": "You can use your voice now! The virus is over."},
    {"id": "57", "type": "virus_start", "text_pt": "Agora você deve usar uma mão apenas. Se usar as duas, bebe 3 goles!", "text_en": "You must now use only one hand. If you use both, drink 3 sips!", "sips": 3},
    {"id": "58", "type": "virus_end", "text_pt": "Pode usar as duas mãos! O vírus acabou.", "text_en": "You can use both hands now! The virus is over."},
    {"id": "59", "type": "virus_start", "text_pt": "{player}, escolha alguém para falar apenas em rimas. Quando essa pessoa acertar 3 rimas, o vírus acaba!", "text_en": "{player}, choose someone to speak only in rhymes. When they get 3 rhymes right, the virus ends!"},
    {"id": "60", "type": "virus_end", "text_pt": "Chega de rimas! O vírus acabou.", "text_en": "No more rhymes! The virus is over."},
    {"id": "61", "type": "virus_start", "text_pt": "{player}, escolha alguém para falar apenas em perguntas. Quando essa pessoa perceber, o vírus acaba!", "text_en": "{player}, choose someone to speak only in questions. When they notice, the virus ends!"},
    {"id": "62", "type": "virus_end", "text_pt": "Pode falar normalmente agora! O vírus acabou.", "text_en": "You can speak normally now! The virus is over."},

    {"id": "63", "type": "bottoms_up", "text_pt": "Todos bebem o que restar nos copos!", "text_en": "Everyone drinks whatever is left in your cups!"},
    {"id": "64", "type": "bottoms_up", "text_pt": "Todos levantem e bebam o que restar!", "text_en": "Everyone stand up and drink whatever is left!"},
    {"id": "65", "type": "bottoms_up", "text_pt": "Todos que estiverem usando preto bebem tudo!", "text_en": "Everyone wearing black drinks it all!"},
    {"id": "66", "type": "bottoms_up", "text_pt": "Todos que estiverem sentados bebem tudo! Levantem e bebam!", "text_en": "Everyone sitting drinks it all! Stand up and drink!"},
    {"id": "67", "type": "bottoms_up", "text_pt": "Todos bebem tudo! Fim de jogo!", "text_en": "Everyone drinks it all! Game over!"},
    {"id": "68", "type": "bottoms_up", "text_pt": "Todos que estiverem com os pés no chão bebem tudo! Levantem os pés e bebam!", "text_en": "Everyone with feet on the floor drinks it all! Lift your feet and drink!"},
    {"id": "69", "type": "bottoms_up", "text_pt": "Você, que está com o telefone, escolha quem vai beber tudo!", "text_en": "You, who is holding the phone, choose who will drink it all!"},
    {"id": "70", "type": "bottoms_up", "text_pt": "O jogador mais à esquerda bebe o conteúdo inteiro do copo!", "text_en": "The leftmost player drinks the entire contents of their cup!"},
    {"id": "71", "type": "bottoms_up", "text_pt": "O jogador mais velho bebe tudo. Sem desculpas!", "text_en": "The oldest player drinks it all. No excuses!"},
    {"id": "72", "type": "bottoms_up", "text_pt": "O jogador que estiver mais longe da saída bebe tudo!", "text_en": "The player farthest from the exit drinks it all!"},
    {"id": "73", "type": "bottoms_up", "text_pt": "Você, que está segurando o copo, beba tudo agora!", "text_en": "You, who is holding your cup, drink it all right now!"},
    {"id": "74", "type": "bottoms_up", "text_pt": "O jogador mais alto bebe tudo! Sem desculpas!", "text_en": "The tallest player drinks it all! No excuses!"},
    {"id": "75", "type": "bottoms_up", "text_pt": "O jogador que estiver com o copo mais cheio bebe tudo!", "text_en": "The player with the fullest cup drinks it all!"},
    {"id": "76", "type": "bottoms_up", "text_pt": "Todos que estiverem com o celular na mão bebem tudo!", "text_en": "Everyone holding a phone drinks it all!"},
    {"id": "77", "type": "bottoms_up", "text_pt": "Todos que tiverem comido algo hoje bebem tudo!", "text_en": "Everyone who has eaten something today drinks it all!"},

    {"id": "78", "type": "normal", "text_pt": "Se você já mandou figurinha errada no zap, beba 2 goles", "text_en": "If you've sent the wrong sticker on WhatsApp, take 2 sips", "sips": 2},
    {"id": "79", "type": "normal", "text_pt": "Se você já acordou pensando que era feriado e não era, beba 3 goles", "text_en": "If you've woken up thinking it was a holiday and it wasn't, take 3 sips", "sips": 3},
    {"id": "80", "type": "normal", "text_pt": "Se você já tentou cozinhar e queimou tudo, beba 3 goles", "text_en": "If you've tried to cook and burned everything, take 3 sips", "sips": 3},
    {"id": "81", "type": "normal", "text_pt": "Se você já esqueceu o paradeiro de algo importante, beba 3 goles", "text_en": "If you've lost something important, take 3 sips", "sips": 3},
    {"id": "82", "type": "normal", "text_pt": "Se você já deu de cara com uma vidraça, beba 3 goles", "text_en": "If you've walked into a glass door, take 3 sips", "sips": 3},
    {"id": "83", "type": "normal", "text_pt": "Se você já tentou ser engraçado e ninguém riu, beba 2 goles", "text_en": "If you've tried to be funny and nobody laughed, take 2 sips", "sips": 2},
    {"id": "84", "type": "normal", "text_pt": "Se você já deixou o celular no banheiro e esqueceu, beba 3 goles", "text_en": "If you've left your phone in the bathroom and forgotten, take 3 sips", "sips": 3},
    {"id": "85", "type": "normal", "text_pt": "Se você já caiu na água com roupa, beba 3 goles", "text_en": "If you've fallen in water with clothes on, take 3 sips", "sips": 3},
    {"id": "86", "type": "normal", "text_pt": "Se você já deu 'oi' para a pessoa errada, beba 2 goles", "text_en": "If you've said hi to the wrong person, take 2 sips", "sips": 2},
    {"id": "87", "type": "normal", "text_pt": "Se você já esqueceu o que ia falar no meio da frase, beba 1 gole", "text_en": "If you've forgotten what you were going to say mid-sentence, take 1 sip", "sips": 1},
    {"id": "88", "type": "normal", "text_pt": "Se você já bateu a cabeça em algo e fingiu que nada aconteceu, beba 2 goles", "text_en": "If you've hit your head on something and pretended nothing happened, take 2 sips", "sips": 2},
    {"id": "89", "type": "normal", "text_pt": "Se você já tentou parecer descolado e falhou, beba 3 goles", "text_en": "If you've tried to look cool and failed miserably, take 3 sips", "sips": 3},
    {"id": "90", "type": "normal", "text_pt": "Se você já falou 'obrigado' para uma máquina, beba 2 goles", "text_en": "If you've said 'thank you' to a machine, take 2 sips", "sips": 2},

    {"id": "91", "type": "game", "text_pt": "Vai passando uma moeda e cada um diz um objeto que começa com a próxima letra do alfabeto. Começa com A e vai até Z. Quem errar bebe 3 goles!", "text_en": "Pass a coin and each person names an object starting with the next letter of the alphabet. Start with A, go to Z. Wrong answer drinks 3 sips!", "sips": 3},
    {"id": "92", "type": "game", "text_pt": "Vai passando uma moeda e cada um diz um número. O mais próximo de {player} ganha e distribui 4 goles!", "text_en": "Pass a coin around and each person says a number. Closest to {player} wins and distributes 4 sips!", "sips": 4},
    {"id": "93", "type": "game", "text_pt": "Vai passando uma moeda e cada um diz um tipo de música. Quem repetir bebe 2 goles!", "text_en": "Pass a coin and each person names a music genre. Anyone who repeats drinks 2 sips!", "sips": 2},
    {"id": "94", "type": "game", "text_pt": "Vai passando uma moeda e cada um diz um objeto de escritório. Quem não conseguir pensar bebe 3 goles!", "text_en": "Pass a coin and each person names a school supply. Anyone who can't think of one drinks 3 sips!", "sips": 3},
    {"id": "95", "type": "game", "text_pt": "Todos devem dizer ao mesmo tempo uma letra. Quem mais combinar com a letra sorteada bebe 2 goles!", "text_en": "Everyone say a letter at the same time. Most matching with the random letter drinks 2 sips!", "sips": 2},
    {"id": "96", "type": "game", "text_pt": "Vai passando uma moeda e cada um diz um animal que começa com a próxima letra. Começa com A. Quem errar bebe 3 goles!", "text_en": "Pass a coin and each person names an animal starting with the next letter. Start with A. Wrong answer drinks 3 sips!", "sips": 3},
    {"id": "97", "type": "game", "text_pt": "Todos devem dizer ao mesmo tempo um número de 1 a 5. Quem mais combinar bebe 2 goles!", "text_en": "Everyone say a number from 1 to 5 at the same time. Most matching drinks 2 sips!", "sips": 2},
    {"id": "98", "type": "game", "text_pt": "Vai passando uma moeda e cada um diz uma fruta. Quem repetir bebe 2 goles!", "text_en": "Pass a coin around and each person names a fruit. Anyone who repeats drinks 2 sips!", "sips": 2},
    {"id": "99", "type": "game", "text_pt": "Todos devem dizer ao mesmo tempo uma cor. Quem mais combinar bebe 2 goles!", "text_en": "Everyone say a color at the same time. Most matching drinks 2 sips!", "sips": 2},
    {"id": "100", "type": "game", "text_pt": "Vai passando uma moeda e cada um diz um esporte. Quem repetir bebe 2 goles!", "text_en": "Pass a coin around and each person names a sport. Anyone who repeats drinks 2 sips!", "sips": 2},

    {"id": "101", "type": "game", "text_pt": "Faça sua melhor imitação de um jogador da mesa. O primeiro a acertar ganha! Todos os outros bebem 2 goles!", "text_en": "Do your best impression of a player at the table. The first to guess correctly wins! Everyone else drinks 2 sips!", "sips": 2},
    {"id": "102", "type": "normal", "text_pt": "Se você fosse assaltar um banco, quais dois jogadores te ajudariam? Todos os outros bebem 3 goles!", "text_en": "If you were going to rob a bank, which two players would help you? Everyone else drinks 3 sips!", "sips": 3},
    {"id": "103", "type": "normal", "text_pt": "Você tem uma tatuagem escondida? Se sim, mostre ao grupo! Se não, beba 3 goles!", "text_en": "Do you have a hidden tattoo? If yes, show the group! If not, take 3 sips!", "sips": 3},
    {"id": "104", "type": "game", "text_pt": "Jogue 'adivinha a música' com o jogador à sua direita. Assubie uma música! Se não adivinhar, ambos bebem 3 goles!", "text_en": "Play 'name that tune' with the player on your right. Hum a song! If they don't guess, you both drink 3 sips!", "sips": 3},
    {"id": "105", "type": "game", "text_pt": "Leia em voz alta a última mensagem do seu celular. Quem rir bebe 2 goles!", "text_en": "Read out loud the last text on your phone. Whoever laughs takes 2 sips!", "sips": 2},
    {"id": "106", "type": "game", "text_pt": "Diga uma palavra feia. Começando pela sua direita, cada jogador segue com uma palavra diferente até alguém errar. Quem errar bebe 3 goles!", "text_en": "Say a curse word. Starting on your right, each player follows with a different curse word until someone messes up. Loser drinks 3 sips!", "sips": 3},
    {"id": "107", "type": "game", "text_pt": "Jogue pegue com um objeto até alguém derrubar. Quem derrubar bebe 3 goles!", "text_en": "Play catch with an item until someone drops it. Loser drinks 3 sips!", "sips": 3},
    {"id": "108", "type": "game", "text_pt": "Desafie um jogador a soletrar uma palavra difícil. Se errar, ele bebe. Se acertar, você bebe 3 goles!", "text_en": "Challenge a player to spell a difficult word. If they spell it wrong, they drink. If they spell it right, you drink 3 sips!", "sips": 3},
    {"id": "109", "type": "game", "text_pt": "Quem você interpretaria em um filme? Se alguém discordar, bebe 2 goles!", "text_en": "Who would you play in a movie? If anyone disagrees, they drink 2 sips!", "sips": 2},
    {"id": "110", "type": "game", "text_pt": "Qual seria seu nome de pornstar? O grupo decide se é bom o suficiente. Se não for, beba 3 goles!", "text_en": "What would your porn name be? The players decide if it's good enough. If not, take 3 sips!", "sips": 3},
    {"id": "111", "type": "game", "text_pt": "Diga uma posição sexual. Começando pela sua direita, cada jogador diz uma até alguém repetir. Quem errar bebe 3 goles!", "text_en": "Name a sex position. Starting on your right, each player must say a sex position until someone repeats. Loser drinks 3 sips!", "sips": 3},
    {"id": "112", "type": "game", "text_pt": "Conte uma história estranha ou engraçada. O grupo precisa adivinhar se é verdade ou mentira. Quem errar bebe 2 goles!", "text_en": "Tell a weird or funny story. Players have to guess if it's true or false. Whoever is wrong drinks 2 sips!", "sips": 2},
    {"id": "113", "type": "game", "text_pt": "Jogue 'luta de polegar' com o jogador à sua esquerda. Quem perder bebe 2 goles!", "text_en": "Have a thumb-war with the person on your left. Loser drinks 2 sips!", "sips": 2},
    {"id": "114", "type": "game", "text_pt": "Se sua casa pegasse fogo e vocês estivessem nela, quem você salvaria primeiro? Todos os outros bebem 3 goles!", "text_en": "If your house was burning down and you were all in it, who would you save first? Everyone else drinks 3 sips!", "sips": 3},
    {"id": "115", "type": "game", "text_pt": "Você daria um tapa na sua mãe por 1 milhão? Quem disse 'sim' bebe 2 goles!", "text_en": "Would you slap your mom for a million dollars? Whoever said 'yes' must take 2 sips!", "sips": 2},
    {"id": "116", "type": "game", "text_pt": "Pense em um número de 1 a 20 e peça ao grupo para adivinhar. Quem mais se aproximar ganha! Todos os outros bebem 2 goles!", "text_en": "Think of a number between 1 and 20 and ask the group to guess. Closest wins! Everyone else drinks 2 sips!", "sips": 2},
    {"id": "117", "type": "game", "text_pt": "Pense em uma posição sexual e peça ao grupo para adivinhar. Quem acertar primeiro ganha! Todos os outros bebem 3 goles!", "text_en": "Think of a sex position and ask the group to guess. First to guess correctly wins! Everyone else drinks 3 sips!", "sips": 3},
    {"id": "118", "type": "game", "text_pt": "Deixe um jogador olhar seu histórico. Se tiver algo pesado, todos bebem 2 goles!", "text_en": "Let a player look at your history. If there is anything naughty, all players take 2 sips!", "sips": 2},
    {"id": "119", "type": "game", "text_pt": "Mostre a última foto do seu celular. Se alguém rir, bebe 2 goles!", "text_en": "Show everyone the last photo on your phone. If anyone laughs, they take 2 sips!", "sips": 2},
    {"id": "120", "type": "game", "text_pt": "O grupo vota em alguém para se exercitar e beber 3 goles!", "text_en": "The group votes on someone to flex their muscles and drink 3 sips!", "sips": 3},
    {"id": "121", "type": "game", "text_pt": "Jogue pedra, papel, tesoura com o jogador à sua esquerda. Quem perder bebe 2 goles, multiplicado pelas empates!", "text_en": "Play rock-paper-scissors with the person on your left. Loser takes 2 sips, multiplied by the number of ties!", "sips": 2},
    {"id": "122", "type": "game", "text_pt": "Olhe fixamente para um jogador à sua escolha. Quem desviar bebe 2 goles!", "text_en": "Have a stare off with a player of your choice. Loser drinks 2 sips!", "sips": 2},
    {"id": "123", "type": "game", "text_pt": "Rime palavras com uma palavra escolhida. Começando pela sua esquerda, cada jogador segue até alguém repetir. Quem errar bebe 2 goles!", "text_en": "Rhyme words with a chosen word. Starting on your left, each player follows until someone repeats. Loser drinks 2 sips!", "sips": 2},
    {"id": "124", "type": "game", "text_pt": "Desafie um jogador para luta de braço. Quem perder bebe 3 goles!", "text_en": "Challenge a person to arm wrestle. Loser drinks 3 sips!", "sips": 3},
    {"id": "125", "type": "game", "text_pt": "Desafie um jogador para manter a pose da árvore. Quem cair primeiro bebe 3 goles!", "text_en": "Challenge someone to keep up the tree pose. Loser drinks 3 sips!", "sips": 3},
    {"id": "126", "type": "game", "text_pt": "Desafie um jogador para não rir. Os outros escolhem um lado e fazem o outro rir. O grupo perdedor bebe 3 goles!", "text_en": "Challenge someone to not laugh. The other players pick a side and make the other person laugh. The losing group drinks 3 sips!", "sips": 3},
    {"id": "127", "type": "game", "text_pt": "A pessoa mais perto de você bebe 2 goles!", "text_en": "The person closest to you drinks 2 sips!", "sips": 2},
    {"id": "128", "type": "game", "text_pt": "A pessoa mais longe de você bebe 2 goles!", "text_en": "The person farthest from you drinks 2 sips!", "sips": 2},
    {"id": "129", "type": "game", "text_pt": "Cada jogador vai perguntar 'nunca fiz'. Quantas vezes você já fez? Beba a quantidade de vezes!", "text_en": "Each player will ask a 'never have I ever' question. How many times have you done it? Drink that many sips!", "sips": 0},
    {"id": "130", "type": "game", "text_pt": "Cada jogador vai perguntar verdadeiro ou falso. Quantas vezes você errou? Beba a quantidade de vezes!", "text_en": "Each player will ask a True or False question. How many times were you wrong? Drink that many sips!", "sips": 0},
    {"id": "131", "type": "normal", "text_pt": "Se você já beijou ou transou com alguém jogando, bebe por beijo e bebe tudo por transar!", "text_en": "If you have kissed or had sex with someone playing, drink for kiss, bottoms up for sex!", "sips": 0, "give_sips": true, "give_sips_amount": 3},
    {"id": "132", "type": "game", "text_pt": "Se você pudesse morar com alguém jogando, quem seria? Todos os outros bebem 2 goles!", "text_en": "If you could live with anyone playing, who would you live with? Everyone else drinks 2 sips!", "sips": 2},
    {"id": "133", "type": "normal", "text_pt": "Se você queria ter transado este mês mas não transou, beba 3 goles!", "text_en": "If you wish you had sex this month but haven't, take 3 sips!", "sips": 3},
    {"id": "134", "type": "game", "text_pt": "Todos devem 'cutucar' uns aos outros e beber 2 goles!", "text_en": "Everyone 'Cheers' each other and drink 2 sips!", "sips": 2},
    {"id": "135", "type": "game", "text_pt": "Se você fosse preso, o que seria? Quem adivinhar ganha! Todos os outros bebem 3 goles!", "text_en": "If you went to jail what would it be for? Whoever guesses correctly wins! Everyone else drinks 3 sips!", "sips": 3},
    {"id": "136", "type": "game", "text_pt": "Qual é meu número de telefone? Quem acertar primeiro ganha! Todos os outros bebem 2 goles!", "text_en": "What's my phone number? Whoever says it first wins! Everyone else drinks 2 sips!", "sips": 2},

    {"id": "137", "type": "normal", "text_pt": "Se você já usou aplicativo de paquera, beba 2 goles", "text_en": "If you have ever used a dating app, take 2 sips", "sips": 2},
    {"id": "138", "type": "normal", "text_pt": "Se você já acordou com ressaca e não lembra como, beba 3 goles", "text_en": "If you've woken up with a hangover and don't remember how, take 3 sips", "sips": 3},
    {"id": "139", "type": "normal", "text_pt": "Se você já enviou print de conversa para a pessoa errada, beba 4 goles", "text_en": "If you've sent a screenshot of a conversation to the wrong person, take 4 sips", "sips": 4},
    {"id": "140", "type": "normal", "text_pt": "Se você já fingiu que não estava em casa quando bateram na porta, beba 2 goles", "text_en": "If you've pretended you weren't home when someone knocked, take 2 sips", "sips": 2},
    {"id": "141", "type": "normal", "text_pt": "Se você já chorou por causa de série, beba 2 goles", "text_en": "If you've cried because of a TV show, take 2 sips", "sips": 2},
    {"id": "142", "type": "normal", "text_pt": "Se você já comeu algo que caiu no chão em menos de 5 segundos, beba 1 gole", "text_en": "If you've eaten something that fell on the floor in less than 5 seconds, take 1 sip", "sips": 1},
    {"id": "143", "type": "normal", "text_pt": "Se você já mandou áudio errado no zap, beba 2 goles", "text_en": "If you've sent a voice message to the wrong person on WhatsApp, take 2 sips", "sips": 2},
    {"id": "144", "type": "normal", "text_pt": "Se você já dormiu no transporte público e passou do ponto, beba 3 goles", "text_en": "If you've fallen asleep on public transport and missed your stop, take 3 sips", "sips": 3},
    {"id": "145", "type": "normal", "text_pt": "Se você já deu like em foto antiga sem querer, beba 3 goles", "text_en": "If you've accidentally liked an old photo, take 3 sips", "sips": 3},
    {"id": "146", "type": "normal", "text_pt": "Se você já fez algo bêbado e não lembra no dia seguinte, beba 4 goles", "text_en": "If you've done something drunk and don't remember the next day, take 4 sips", "sips": 4},
    {"id": "147", "type": "normal", "text_pt": "Se você já fingiu que estava doente para não ir em evento, beba 2 goles", "text_en": "If you've pretended to be sick to avoid an event, take 2 sips", "sips": 2},
    {"id": "148", "type": "normal", "text_pt": "Se você já ligou para o 190 sem querer, beba 4 goles", "text_en": "If you've accidentally called emergency, take 4 sips", "sips": 4},
    {"id": "149", "type": "normal", "text_pt": "Se você já mandou 'eu te amo' para a pessoa errada, beba 4 goles", "text_en": "If you've sent 'I love you' to the wrong person, take 4 sips", "sips": 4},
    {"id": "150", "type": "normal", "text_pt": "Se você já esqueceu de desligar o fogão, beba 3 goles", "text_en": "If you've forgotten to turn off the stove, take 3 sips", "sips": 3},

    {"id": "151", "type": "game", "text_pt": "Se seu nome começa com vogal, beba 2 goles!", "text_en": "If your name starts with a vowel, take 2 sips!", "sips": 2},
    {"id": "152", "type": "game", "text_pt": "Se seu nome começa com consoante, beba 2 goles!", "text_en": "If your name starts with a consonant, take 2 sips!", "sips": 2},
    {"id": "153", "type": "game", "text_pt": "O jogador mais baixo bebe 2 goles!", "text_en": "The shortest player drinks 2 sips!", "sips": 2},
    {"id": "154", "type": "game", "text_pt": "Se você tem cabelo loiro, beba 2 goles!", "text_en": "If you have blonde hair, take 2 sips!", "sips": 2},
    {"id": "155", "type": "game", "text_pt": "O jogador mais alto bebe 2 goles!", "text_en": "The tallest player drinks 2 sips!", "sips": 2},
    {"id": "156", "type": "game", "text_pt": "Se você mora com seus pais, beba 2 goles!", "text_en": "If you live with your parents, take 2 sips!", "sips": 2},
    {"id": "157", "type": "game", "text_pt": "Se você tem cabelo vermelho, beba 2 goles!", "text_en": "If you have red hair, take 2 sips!", "sips": 2},
    {"id": "158", "type": "game", "text_pt": "Se você tem cabelo castanho, beba 2 goles!", "text_en": "If you have brown hair, take 2 sips!", "sips": 2},
    {"id": "159", "type": "game", "text_pt": "Se você já usou aplicativo de paquera, beba 2 goles!", "text_en": "If you have ever used a dating app, take 2 sips!", "sips": 2},
    {"id": "160", "type": "game", "text_pt": "Se você tem renda na calcinha ou não está de calcinha nenhuma, beba 2 goles!", "text_en": "If you have lace on your underwear or no underwear on at all, take 2 sips!", "sips": 2},
    {"id": "161", "type": "game", "text_pt": "Qual presidente aparece na nota de 20 dólares? Se não souber, beba 2 goles!", "text_en": "What president appears on the US twenty-dollar bill? If you don't know, take 2 sips!", "sips": 2},

    {"id": "162", "type": "bottoms_up", "text_pt": "Quem estiver com vodka bebe tudo! Sem desculpas!", "text_en": "Whoever is drinking vodka, bottoms up! No excuses!"},
    {"id": "163", "type": "bottoms_up", "text_pt": "Quem estiver com cerveja bebe tudo! Sem desculpas!", "text_en": "Whoever is drinking beer, bottoms up! No excuses!"},
    {"id": "164", "type": "bottoms_up", "text_pt": "Todos votam em alguém para beber tudo! Em caso de empate, todos bebem!", "text_en": "Everyone must vote on someone to bottoms up! In case of a tie, everyone drinks!"},
    {"id": "165", "type": "bottoms_up", "text_pt": "Se você é membro da NIAEFEUP, beba tudo! Sem desculpas!", "text_en": "If you are a member of NIAEFEUP, bottoms up! No excuses!"},

    {"id": "166", "type": "virus_start", "text_pt": "Espalhe o vírus! Escolha outro jogador para beber o dobro do que você beber até ser dito o contrário!", "text_en": "Spread the virus! Choose another player to drink double whatever you drink until said otherwise!"},
    {"id": "167", "type": "virus_end", "text_pt": "O duo infectado está curado! Sem mais bebida dupla!", "text_en": "The infected duo are healed! No more double drinking!"},
    {"id": "168", "type": "virus_start", "text_pt": "Você é o mestre das regras! Crie uma regra para todos até ser dito o contrário!", "text_en": "You are the rule master! Create a rule for everyone until said otherwise!"},
    {"id": "169", "type": "virus_end", "text_pt": "O trono foi tomado! Sem mais regras para todos!", "text_en": "The throne is taken! No more rules for everyone!"},
    {"id": "170", "type": "virus_start", "text_pt": "Hora do Sugoi! Você deve agir como uma garota anime kawaii, com sons e tudo!", "text_en": "Sugoi time! You must act like a kawaii cute anime girl, sounds and everything!"},
    {"id": "171", "type": "virus_end", "text_pt": "Baka!! Sem mais cosplay anime, você está livre!", "text_en": "Baka!! No more anime cosplay, you are free!"}
  ]
}
